xmltodict3/__init__.py
xmltodict3/exceptions.py
xmltodict3/transformers.py
xmltodict3/xml_to_dict.py
xmltodict3-0.0.4.dist-info/LICENSE
xmltodict3-0.0.4.dist-info/METADATA
xmltodict3-0.0.4.dist-info/WHEEL
xmltodict3-0.0.4.dist-info/top_level.txt
xmltodict3-0.0.4.dist-info/RECORD
