Metadata-Version: 2.1
Name: xmltodict3
Version: 0.0.4
Summary: An open-source library that is used for converting XML to a python dictionary.
Home-page: https://github.com/dart-neitro/xmltodict3
Author: Konstantin Neitro
Author-email: neitro88@gmail.com
License: UNKNOWN
Platform: UNKNOWN
Classifier: Programming Language :: Python :: 3
Classifier: License :: OSI Approved :: MIT License
Classifier: Operating System :: OS Independent
Requires-Python: >=3.5
